{
    "tester": "opencl",
    "generator": {
        "exec": "../lib/CLSmith/build/CLSmith"
    },
    "preflight_checks": [

    ],
    "duts": [
        {
            "platform": "oclgrind",
            "device": "foobar"
        },
        {
            "platform": "intel",
            "device": "foobar"
        },
        {
            "platform": "computeaorta",
            "device": "foobar"
        }
    ],
    "comparator": {
    },
    "postflight_checks": [
    ],
    "reducer": {
    }
}
